easytree/__init__.py
easytree/types.py
easytree/utils.py
tests/__init__.py
tests/types.py
tests/utils.py
easytree-1.0.0.dist-info/LICENSE
easytree-1.0.0.dist-info/METADATA
easytree-1.0.0.dist-info/WHEEL
easytree-1.0.0.dist-info/top_level.txt
easytree-1.0.0.dist-info/RECORD
