Metadata-Version: 2.1
Name: easytree
Version: 1.0.0
Summary: A recursive dot-styled defaultdict to read and write deeply-nested trees
Home-page: https://easytree.readthedocs.io/en/latest
Author: David Schenck
Author-email: david.schenck@outlook.com
Classifier: Programming Language :: Python :: 3
Classifier: License :: OSI Approved :: MIT License
Classifier: Operating System :: OS Independent
License-File: LICENSE
